[null,{"json_class":"RPG::Armor","@description":"Vêtements ne protégeant pas du tout.","@name":"Vêtements de tissu","@icon_index":168,"@price":100,"@note":"","@id":1,"@features":[{"json_class":"RPG::BaseItem::Feature","@code":22,"@data_id":1,"@value":0}],"@params":[0,0,0,1,0,0,0,0],"@etype_id":3,"@atype_id":1},{"json_class":"RPG::Armor","@description":"En cuir simple.","@name":"Vêtements","@icon_index":168,"@price":300,"@note":"","@id":2,"@features":[{"json_class":"RPG::BaseItem::Feature","@code":22,"@data_id":1,"@value":0}],"@params":[0,0,0,5,0,0,0,0],"@etype_id":3,"@atype_id":1},{"json_class":"RPG::Armor","@description":"Vêtement usé et ayant déjà servi à l'aventure.","@name":"Habit d'aventurier","@icon_index":168,"@price":2000,"@note":"","@id":3,"@features":[{"json_class":"RPG::BaseItem::Feature","@code":22,"@data_id":1,"@value":0}],"@params":[0,0,0,10,0,0,0,0],"@etype_id":3,"@atype_id":1},{"json_class":"RPG::Armor","@description":"En cuir renforcé !","@name":"Vêtements en cuir","@icon_index":168,"@price":5000,"@note":"","@id":4,"@features":[{"json_class":"RPG::BaseItem::Feature","@code":22,"@data_id":1,"@value":0}],"@params":[0,0,0,15,0,0,0,0],"@etype_id":3,"@atype_id":1},{"json_class":"RPG::Armor","@description":"Vêtement fait d'acier renforcé.","@name":"Brigandine","@icon_index":168,"@price":8000,"@note":"","@id":5,"@features":[{"json_class":"RPG::BaseItem::Feature","@code":22,"@data_id":1,"@value":0}],"@params":[0,0,0,20,0,0,0,0],"@etype_id":3,"@atype_id":1},{"json_class":"RPG::Armor","@description":"Bandeau protégeant la tête.","@name":"Bandana","@icon_index":162,"@price":100,"@note":"","@id":6,"@features":[{"json_class":"RPG::BaseItem::Feature","@code":22,"@data_id":1,"@value":0}],"@params":[0,0,0,1,0,0,0,0],"@etype_id":2,"@atype_id":1},{"json_class":"RPG::Armor","@description":"Un bandana renforcé en cuir.","@name":"Bandana en cuir","@icon_index":162,"@price":500,"@note":"","@id":7,"@features":[{"json_class":"RPG::BaseItem::Feature","@code":22,"@data_id":1,"@value":0}],"@params":[0,0,0,3,0,0,0,0],"@etype_id":2,"@atype_id":1},{"json_class":"RPG::Armor","@description":"Protège du froid.","@name":"Chapeau fourré","@icon_index":162,"@price":1500,"@note":"","@id":8,"@features":[{"json_class":"RPG::BaseItem::Feature","@code":22,"@data_id":1,"@value":0}],"@params":[0,0,0,6,0,0,0,0],"@etype_id":2,"@atype_id":1},{"json_class":"RPG::Armor","@description":"Épais tissu enroulé autour de la tête.","@name":"Turban","@icon_index":162,"@price":4000,"@note":"","@id":9,"@features":[{"json_class":"RPG::BaseItem::Feature","@code":22,"@data_id":1,"@value":0}],"@params":[0,0,0,10,0,0,0,0],"@etype_id":2,"@atype_id":1},{"json_class":"RPG::Armor","@description":"Chapeau plumé très stylisé.","@name":"Chapeau","@icon_index":162,"@price":6500,"@note":"","@id":10,"@features":[{"json_class":"RPG::BaseItem::Feature","@code":22,"@data_id":1,"@value":0}],"@params":[0,0,0,14,0,0,0,0],"@etype_id":2,"@atype_id":1},{"json_class":"RPG::Armor","@description":"Une robe faite d'épais coton.","@name":"Robe en coton","@icon_index":171,"@price":100,"@note":"","@id":11,"@features":[{"json_class":"RPG::BaseItem::Feature","@code":22,"@data_id":1,"@value":0}],"@params":[0,0,0,4,2,2,0,0],"@etype_id":3,"@atype_id":2},{"json_class":"RPG::Armor","@description":"Une cape faite de fine soie.","@name":"Cape en soie","@icon_index":171,"@price":500,"@note":"","@id":12,"@features":[{"json_class":"RPG::BaseItem::Feature","@code":22,"@data_id":1,"@value":0}],"@params":[0,0,0,9,3,4,0,0],"@etype_id":3,"@atype_id":2},{"json_class":"RPG::Armor","@description":"Une robe légère sur laquelle sont inscrites des runes.","@name":"Robe runique","@icon_index":171,"@price":3000,"@note":"","@id":13,"@features":[{"json_class":"RPG::BaseItem::Feature","@code":22,"@data_id":1,"@value":0}],"@params":[0,0,0,13,6,7,0,0],"@etype_id":3,"@atype_id":2},{"json_class":"RPG::Armor","@description":"Robe portée par un sage vieil homme.","@name":"Robe de l'ermite","@icon_index":171,"@price":8000,"@note":"","@id":14,"@features":[{"json_class":"RPG::BaseItem::Feature","@code":22,"@data_id":1,"@value":0},{"json_class":"RPG::BaseItem::Feature","@code":11,"@data_id":3,"@value":0.8},{"json_class":"RPG::BaseItem::Feature","@code":11,"@data_id":4,"@value":0.8},{"json_class":"RPG::BaseItem::Feature","@code":11,"@data_id":5,"@value":0.8},{"json_class":"RPG::BaseItem::Feature","@code":11,"@data_id":6,"@value":0.8},{"json_class":"RPG::BaseItem::Feature","@code":11,"@data_id":7,"@value":0.8},{"json_class":"RPG::BaseItem::Feature","@code":11,"@data_id":8,"@value":0.8}],"@params":[0,0,0,18,11,12,0,0],"@etype_id":3,"@atype_id":2},{"json_class":"RPG::Armor","@description":"Cette cape est imprégnée du pouvoir des esprits.\r\nAugmente la résistance magique.","@name":"Cape élémentale","@icon_index":171,"@price":13000,"@note":"","@id":15,"@features":[{"json_class":"RPG::BaseItem::Feature","@code":22,"@data_id":1,"@value":0},{"json_class":"RPG::BaseItem::Feature","@code":11,"@data_id":3,"@value":0.6},{"json_class":"RPG::BaseItem::Feature","@code":11,"@data_id":4,"@value":0.6},{"json_class":"RPG::BaseItem::Feature","@code":11,"@data_id":5,"@value":0.6},{"json_class":"RPG::BaseItem::Feature","@code":11,"@data_id":6,"@value":0.6},{"json_class":"RPG::BaseItem::Feature","@code":11,"@data_id":7,"@value":0.6},{"json_class":"RPG::BaseItem::Feature","@code":11,"@data_id":8,"@value":0.6}],"@params":[0,0,0,25,17,18,0,0],"@etype_id":3,"@atype_id":2},{"json_class":"RPG::Armor","@description":"Un accessoire pour cheveux en cuivre.","@name":"Couronne de cuivre","@icon_index":166,"@price":100,"@note":"","@id":16,"@features":[{"json_class":"RPG::BaseItem::Feature","@code":22,"@data_id":1,"@value":0}],"@params":[0,0,0,2,2,1,0,0],"@etype_id":2,"@atype_id":2},{"json_class":"RPG::Armor","@description":"Un accessoire en forme de cercle.","@name":"Couronne","@icon_index":166,"@price":400,"@note":"","@id":17,"@features":[{"json_class":"RPG::BaseItem::Feature","@code":22,"@data_id":1,"@value":0}],"@params":[0,0,0,6,4,3,0,0],"@etype_id":2,"@atype_id":2},{"json_class":"RPG::Armor","@description":"Accessoire améliorant la magie de son porteur.","@name":"Épingle d'argent","@icon_index":166,"@price":2500,"@note":"","@id":18,"@features":[{"json_class":"RPG::BaseItem::Feature","@code":22,"@data_id":1,"@value":0}],"@params":[0,0,0,10,5,4,0,0],"@etype_id":2,"@atype_id":2},{"json_class":"RPG::Armor","@description":"Une couronne faite d'un métal magique, le mithril.","@name":"Couronne de mithril","@icon_index":166,"@price":6000,"@note":"","@id":19,"@features":[{"json_class":"RPG::BaseItem::Feature","@code":22,"@data_id":1,"@value":0}],"@params":[0,0,0,15,7,6,0,0],"@etype_id":2,"@atype_id":2},{"json_class":"RPG::Armor","@description":"Enchantée par une mystique civilisation oubliée...","@name":"Couronne de Magi","@icon_index":166,"@price":10000,"@note":"","@id":20,"@features":[{"json_class":"RPG::BaseItem::Feature","@code":22,"@data_id":1,"@value":0}],"@params":[0,0,0,18,12,11,0,0],"@etype_id":2,"@atype_id":2},{"json_class":"RPG::Armor","@description":"Armure faite de cuir.","@name":"Armure de cuir","@icon_index":169,"@price":100,"@note":"","@id":21,"@features":[{"json_class":"RPG::BaseItem::Feature","@code":22,"@data_id":1,"@value":0}],"@params":[0,0,0,5,0,0,0,0],"@etype_id":3,"@atype_id":3},{"json_class":"RPG::Armor","@description":"Un plastron fait de bronze.","@name":"Armure de bronze","@icon_index":169,"@price":400,"@note":"","@id":22,"@features":[{"json_class":"RPG::BaseItem::Feature","@code":22,"@data_id":1,"@value":0}],"@params":[0,0,0,12,0,0,0,0],"@etype_id":3,"@atype_id":3},{"json_class":"RPG::Armor","@description":"Un plastron fait d'acier.","@name":"Plastron d'acier","@icon_index":169,"@price":2700,"@note":"","@id":23,"@features":[{"json_class":"RPG::BaseItem::Feature","@code":22,"@data_id":1,"@value":0}],"@params":[0,0,0,18,0,0,-2,0],"@etype_id":3,"@atype_id":3},{"json_class":"RPG::Armor","@description":"Un plastron fait d'un métal magique, le mithril.","@name":"Plastron de mithril","@icon_index":169,"@price":7000,"@note":"","@id":24,"@features":[{"json_class":"RPG::BaseItem::Feature","@code":22,"@data_id":1,"@value":0}],"@params":[0,0,0,24,0,0,0,0],"@etype_id":3,"@atype_id":3},{"json_class":"RPG::Armor","@description":"Un plastron fait d'écailles de dragons.","@name":"Plastron de dragon","@icon_index":169,"@price":12000,"@note":"","@id":25,"@features":[{"json_class":"RPG::BaseItem::Feature","@code":22,"@data_id":1,"@value":0},{"json_class":"RPG::BaseItem::Feature","@code":11,"@data_id":3,"@value":0.8}],"@params":[0,0,0,30,0,0,0,0],"@etype_id":3,"@atype_id":3},{"json_class":"RPG::Armor","@description":"Un casque fait de cuir.","@name":"Casque de cuir","@icon_index":163,"@price":100,"@note":"","@id":26,"@features":[{"json_class":"RPG::BaseItem::Feature","@code":22,"@data_id":1,"@value":0}],"@params":[0,0,0,4,0,0,0,0],"@etype_id":2,"@atype_id":3},{"json_class":"RPG::Armor","@description":"Un casque fait de bronze.","@name":"Casque de bronze","@icon_index":163,"@price":350,"@note":"","@id":27,"@features":[{"json_class":"RPG::BaseItem::Feature","@code":22,"@data_id":1,"@value":0}],"@params":[0,0,0,7,0,0,0,0],"@etype_id":2,"@atype_id":3},{"json_class":"RPG::Armor","@description":"Un casque fait d'acier.","@name":"Sarett","@icon_index":163,"@price":2400,"@note":"","@id":28,"@features":[{"json_class":"RPG::BaseItem::Feature","@code":22,"@data_id":1,"@value":0}],"@params":[0,0,0,12,0,0,0,0],"@etype_id":2,"@atype_id":3},{"json_class":"RPG::Armor","@description":"Un casque fait d'un métal magique, le mithril.","@name":"Casque de mithril","@icon_index":163,"@price":5500,"@note":"","@id":29,"@features":[{"json_class":"RPG::BaseItem::Feature","@code":22,"@data_id":1,"@value":0}],"@params":[0,0,0,16,0,0,0,0],"@etype_id":2,"@atype_id":3},{"json_class":"RPG::Armor","@description":"Un casque fait d'écailles de dragons.","@name":"Casque de dragon","@icon_index":163,"@price":9500,"@note":"","@id":30,"@features":[{"json_class":"RPG::BaseItem::Feature","@code":22,"@data_id":1,"@value":0},{"json_class":"RPG::BaseItem::Feature","@code":11,"@data_id":3,"@value":0.8}],"@params":[0,0,0,22,0,0,0,0],"@etype_id":2,"@atype_id":3},{"json_class":"RPG::Armor","@description":"Armure faite de lourdes chaînes.","@name":"Cotte de mailles","@icon_index":170,"@price":100,"@note":"","@id":31,"@features":[{"json_class":"RPG::BaseItem::Feature","@code":22,"@data_id":1,"@value":0.0},{"json_class":"RPG::BaseItem::Feature","@code":33,"@data_id":0,"@value":-1.0}],"@params":[0,0,0,8,0,0,0,0],"@etype_id":3,"@atype_id":4},{"json_class":"RPG::Armor","@description":"Armure assurant une bonne protection.","@name":"Armure d'acier","@icon_index":170,"@price":800,"@note":"","@id":32,"@features":[{"json_class":"RPG::BaseItem::Feature","@code":22,"@data_id":1,"@value":-0.01},{"json_class":"RPG::BaseItem::Feature","@code":33,"@data_id":0,"@value":-2.0}],"@params":[0,0,0,16,0,0,0,0],"@etype_id":3,"@atype_id":4},{"json_class":"RPG::Armor","@description":"Une très bonne armure surtout utilisée par les chevaliers.","@name":"Armure de chevalier","@icon_index":170,"@price":3600,"@note":"","@id":33,"@features":[{"json_class":"RPG::BaseItem::Feature","@code":22,"@data_id":1,"@value":-0.02},{"json_class":"RPG::BaseItem::Feature","@code":33,"@data_id":0,"@value":-3.0}],"@params":[0,0,0,24,0,0,0,0],"@etype_id":3,"@atype_id":4},{"json_class":"RPG::Armor","@description":"Une armure faite d'un métal magique, le mithril.","@name":"Armure de mithril","@icon_index":170,"@price":8000,"@note":"","@id":34,"@features":[{"json_class":"RPG::BaseItem::Feature","@code":22,"@data_id":1,"@value":0}],"@params":[0,0,0,32,0,0,0,0],"@etype_id":3,"@atype_id":4},{"json_class":"RPG::Armor","@description":"Faite d'écailles de dragons.","@name":"Armure de dragon","@icon_index":170,"@price":15000,"@note":"","@id":35,"@features":[{"json_class":"RPG::BaseItem::Feature","@code":22,"@data_id":1,"@value":-0.01},{"json_class":"RPG::BaseItem::Feature","@code":11,"@data_id":3,"@value":0.8},{"json_class":"RPG::BaseItem::Feature","@code":33,"@data_id":0,"@value":-2.0}],"@params":[0,0,0,40,0,0,0,0],"@etype_id":3,"@atype_id":4},{"json_class":"RPG::Armor","@description":"Casque fait de lourdes chaînes.","@name":"Heaume de mailles","@icon_index":164,"@price":100,"@note":"","@id":36,"@features":[{"json_class":"RPG::BaseItem::Feature","@code":22,"@data_id":1,"@value":0.0},{"json_class":"RPG::BaseItem::Feature","@code":33,"@data_id":0,"@value":-1.0}],"@params":[0,0,0,6,0,0,0,0],"@etype_id":2,"@atype_id":4},{"json_class":"RPG::Armor","@description":"Un heaume fait d'acier.","@name":"Heaume d'acier","@icon_index":164,"@price":600,"@note":"","@id":37,"@features":[{"json_class":"RPG::BaseItem::Feature","@code":22,"@data_id":1,"@value":-0.005},{"json_class":"RPG::BaseItem::Feature","@code":33,"@data_id":0,"@value":-2.0}],"@params":[0,0,0,12,0,0,0,0],"@etype_id":2,"@atype_id":4},{"json_class":"RPG::Armor","@description":"Un très bon heaume surtout utilisé par les chevaliers.","@name":"Heaume de chevalier","@icon_index":164,"@price":3000,"@note":"","@id":38,"@features":[{"json_class":"RPG::BaseItem::Feature","@code":22,"@data_id":1,"@value":-0.01},{"json_class":"RPG::BaseItem::Feature","@code":33,"@data_id":0,"@value":-3.0}],"@params":[0,0,0,18,0,0,0,0],"@etype_id":2,"@atype_id":4},{"json_class":"RPG::Armor","@description":"Un heaume fait d'un métal magique, le mithril.","@name":"Heaume de mithril","@icon_index":164,"@price":7000,"@note":"","@id":39,"@features":[{"json_class":"RPG::BaseItem::Feature","@code":22,"@data_id":1,"@value":0}],"@params":[0,0,0,24,0,0,0,0],"@etype_id":2,"@atype_id":4},{"json_class":"RPG::Armor","@description":"Un heaume fait d'écailles de dragons","@name":"Heaume de dragon","@icon_index":164,"@price":12000,"@note":"","@id":40,"@features":[{"json_class":"RPG::BaseItem::Feature","@code":22,"@data_id":1,"@value":-0.005},{"json_class":"RPG::BaseItem::Feature","@code":11,"@data_id":3,"@value":0.8},{"json_class":"RPG::BaseItem::Feature","@code":33,"@data_id":0,"@value":-2.0}],"@params":[0,0,0,30,0,0,0,0],"@etype_id":2,"@atype_id":4},{"json_class":"RPG::Armor","@description":"Un petit bouclier utilisé pour parer les attaques.","@name":"Targe","@icon_index":160,"@price":100,"@note":"","@id":41,"@features":[{"json_class":"RPG::BaseItem::Feature","@code":22,"@data_id":1,"@value":0.02}],"@params":[0,0,0,1,0,0,0,0],"@etype_id":1,"@atype_id":5},{"json_class":"RPG::Armor","@description":"Un bouclier rond en acier renforcé.","@name":"Targe ronde","@icon_index":160,"@price":300,"@note":"","@id":42,"@features":[{"json_class":"RPG::BaseItem::Feature","@code":22,"@data_id":1,"@value":0.04}],"@params":[0,0,0,3,0,0,0,0],"@etype_id":1,"@atype_id":5},{"json_class":"RPG::Armor","@description":"Une targe recouverte de piques.\r\nPermet une meilleure défense.","@name":"Targe cloutée","@icon_index":160,"@price":1800,"@note":"","@id":43,"@features":[{"json_class":"RPG::BaseItem::Feature","@code":22,"@data_id":1,"@value":0.06}],"@params":[0,0,3,6,0,0,0,0],"@etype_id":1,"@atype_id":5},{"json_class":"RPG::Armor","@description":"Une targe faite d'un métal magique, le mithril.","@name":"Targe de mithril","@icon_index":160,"@price":4500,"@note":"","@id":44,"@features":[{"json_class":"RPG::BaseItem::Feature","@code":22,"@data_id":1,"@value":0.08}],"@params":[0,0,0,10,0,0,0,0],"@etype_id":1,"@atype_id":5},{"json_class":"RPG::Armor","@description":"Une targe faite d'écailles de dragons.","@name":"Targe de dragon","@icon_index":160,"@price":7000,"@note":"","@id":45,"@features":[{"json_class":"RPG::BaseItem::Feature","@code":22,"@data_id":1,"@value":0.125},{"json_class":"RPG::BaseItem::Feature","@code":11,"@data_id":3,"@value":0.8}],"@params":[0,0,0,15,0,0,0,0],"@etype_id":1,"@atype_id":5},{"json_class":"RPG::Armor","@description":"Un bouclier fait de bois solide.","@name":"Bouclier de bois","@icon_index":161,"@price":100,"@note":"","@id":46,"@features":[{"json_class":"RPG::BaseItem::Feature","@code":22,"@data_id":1,"@value":0.0},{"json_class":"RPG::BaseItem::Feature","@code":22,"@data_id":3,"@value":-0.2},{"json_class":"RPG::BaseItem::Feature","@code":33,"@data_id":0,"@value":-1.0}],"@params":[0,0,0,2,0,0,0,0],"@etype_id":1,"@atype_id":6},{"json_class":"RPG::Armor","@description":"Un bouclier fait de fer.","@name":"Bouclier de fer","@icon_index":161,"@price":700,"@note":"","@id":47,"@features":[{"json_class":"RPG::BaseItem::Feature","@code":22,"@data_id":1,"@value":0.0},{"json_class":"RPG::BaseItem::Feature","@code":22,"@data_id":3,"@value":-0.2},{"json_class":"RPG::BaseItem::Feature","@code":33,"@data_id":0,"@value":-2.0}],"@params":[0,0,0,6,0,0,0,0],"@etype_id":1,"@atype_id":6},{"json_class":"RPG::Armor","@description":"Un très bon bouclier surtout utilisé par les chevaliers.","@name":"Bouclier de chevalier","@icon_index":161,"@price":3400,"@note":"","@id":48,"@features":[{"json_class":"RPG::BaseItem::Feature","@code":22,"@data_id":1,"@value":0.0},{"json_class":"RPG::BaseItem::Feature","@code":22,"@data_id":3,"@value":-0.2},{"json_class":"RPG::BaseItem::Feature","@code":33,"@data_id":0,"@value":-3.0}],"@params":[0,0,0,12,0,0,0,0],"@etype_id":1,"@atype_id":6},{"json_class":"RPG::Armor","@description":"Un bouclier fait d'un métal magique, le mithril.","@name":"Bouclier de mithril","@icon_index":510,"@price":7500,"@note":"","@id":49,"@features":[{"json_class":"RPG::BaseItem::Feature","@code":22,"@data_id":1,"@value":0},{"json_class":"RPG::BaseItem::Feature","@code":22,"@data_id":3,"@value":-0.2}],"@params":[0,0,0,18,0,0,0,0],"@etype_id":1,"@atype_id":6},{"json_class":"RPG::Armor","@description":"Un bouclier fait d'écailles de dragons.","@name":"Bouclier de dragon","@icon_index":161,"@price":13500,"@note":"","@id":50,"@features":[{"json_class":"RPG::BaseItem::Feature","@code":22,"@data_id":1,"@value":0.0},{"json_class":"RPG::BaseItem::Feature","@code":22,"@data_id":3,"@value":-0.2},{"json_class":"RPG::BaseItem::Feature","@code":11,"@data_id":3,"@value":0.8},{"json_class":"RPG::BaseItem::Feature","@code":33,"@data_id":0,"@value":-2.0}],"@params":[0,0,0,24,0,0,0,0],"@etype_id":1,"@atype_id":6},{"json_class":"RPG::Armor","@description":"Une ceinture sur laquelle est gravée le nom de Kratos.\r\nAugmente l'attaque.","@name":"Ceinture guerrière","@icon_index":179,"@price":3000,"@note":"","@id":51,"@features":[{"json_class":"RPG::BaseItem::Feature","@code":22,"@data_id":1,"@value":0}],"@params":[0,0,10,0,0,0,0,0],"@etype_id":4,"@atype_id":1},{"json_class":"RPG::Armor","@description":"Son porteur voit sa défense renforcée.","@name":"Amulette guerrière","@icon_index":179,"@price":3000,"@note":"","@id":52,"@features":[{"json_class":"RPG::BaseItem::Feature","@code":22,"@data_id":1,"@value":0}],"@params":[0,0,0,10,0,10,0,0],"@etype_id":4,"@atype_id":1},{"json_class":"RPG::Armor","@description":"Ces bottes sont habitées d'un esprit de la forêt.","@name":"Bottes ailées","@icon_index":179,"@price":3000,"@note":"","@id":53,"@features":[{"json_class":"RPG::BaseItem::Feature","@code":22,"@data_id":1,"@value":0.1}],"@params":[0,0,0,0,0,0,10,0],"@etype_id":4,"@atype_id":1},{"json_class":"RPG::Armor","@description":"Le pouvoir de la terre protège son porteur des\r\naltérations d'état.","@name":"Médaillon de la terre","@icon_index":179,"@price":3000,"@note":"","@id":54,"@features":[{"json_class":"RPG::BaseItem::Feature","@code":22,"@data_id":1,"@value":0},{"json_class":"RPG::BaseItem::Feature","@code":13,"@data_id":2,"@value":0.8},{"json_class":"RPG::BaseItem::Feature","@code":13,"@data_id":3,"@value":0.8},{"json_class":"RPG::BaseItem::Feature","@code":13,"@data_id":4,"@value":0.8},{"json_class":"RPG::BaseItem::Feature","@code":13,"@data_id":5,"@value":0.8},{"json_class":"RPG::BaseItem::Feature","@code":13,"@data_id":6,"@value":0.8},{"json_class":"RPG::BaseItem::Feature","@code":13,"@data_id":7,"@value":0.8}],"@params":[0,0,0,5,0,0,0,0],"@etype_id":4,"@atype_id":1},{"json_class":"RPG::Armor","@description":"Ce charme agit comme un trèfle à 4 feuilles.","@name":"Charme de chance","@icon_index":179,"@price":5000,"@note":"","@id":55,"@features":[{"json_class":"RPG::BaseItem::Feature","@code":22,"@data_id":1,"@value":0}],"@params":[0,0,0,0,0,0,0,30],"@etype_id":4,"@atype_id":1},{"json_class":"RPG::Armor","@description":"Un accessoire porté par les croyants.","@name":"Symbole mystique","@icon_index":179,"@price":5000,"@note":"","@id":56,"@features":[{"json_class":"RPG::BaseItem::Feature","@code":22,"@data_id":1,"@value":0},{"json_class":"RPG::BaseItem::Feature","@code":11,"@data_id":3,"@value":0.8},{"json_class":"RPG::BaseItem::Feature","@code":11,"@data_id":4,"@value":0.8},{"json_class":"RPG::BaseItem::Feature","@code":11,"@data_id":5,"@value":0.8},{"json_class":"RPG::BaseItem::Feature","@code":11,"@data_id":6,"@value":0.8},{"json_class":"RPG::BaseItem::Feature","@code":11,"@data_id":7,"@value":0.8},{"json_class":"RPG::BaseItem::Feature","@code":11,"@data_id":8,"@value":0.8}],"@params":[0,0,0,0,0,5,0,0],"@etype_id":4,"@atype_id":1},{"json_class":"RPG::Armor","@description":"Un anneau qui cache le pouvoir d'un génie.","@name":"Anneau de Salomon","@icon_index":179,"@price":5000,"@note":"","@id":57,"@features":[{"json_class":"RPG::BaseItem::Feature","@code":22,"@data_id":1,"@value":0},{"json_class":"RPG::BaseItem::Feature","@code":23,"@data_id":4,"@value":0.5}],"@params":[0,0,0,0,10,0,0,0],"@etype_id":4,"@atype_id":1},{"json_class":"RPG::Armor","@description":"Ce collier renforce grandement son porteur.","@name":"Collier d'Odin","@icon_index":179,"@price":5000,"@note":"","@id":58,"@features":[{"json_class":"RPG::BaseItem::Feature","@code":22,"@data_id":0,"@value":0.1},{"json_class":"RPG::BaseItem::Feature","@code":22,"@data_id":1,"@value":0.1},{"json_class":"RPG::BaseItem::Feature","@code":22,"@data_id":9,"@value":0.06}],"@params":[0,0,0,0,0,0,0,0],"@etype_id":4,"@atype_id":1},{"json_class":"RPG::Armor","@description":"Un cache-oeil qui augmente l'attaque de son porteur,\r\nau détriment de sa défense.","@name":"Bandeau du guerrier","@icon_index":179,"@price":5000,"@note":"","@id":59,"@features":[{"json_class":"RPG::BaseItem::Feature","@code":22,"@data_id":1,"@value":-0.05}],"@params":[0,0,15,-5,0,0,0,0],"@etype_id":4,"@atype_id":1},{"json_class":"RPG::Armor","@description":"Le plus grand des Dieux réside dans cet unique talisman.","@name":"Talisman de la lumière","@icon_index":179,"@price":5000,"@note":"","@id":60,"@features":[{"json_class":"RPG::BaseItem::Feature","@code":22,"@data_id":0,"@value":0.05},{"json_class":"RPG::BaseItem::Feature","@code":22,"@data_id":1,"@value":0.05},{"json_class":"RPG::BaseItem::Feature","@code":22,"@data_id":7,"@value":0.04}],"@params":[0,0,5,5,5,5,5,5],"@etype_id":4,"@atype_id":1}]